odoo/addons/product_supplierinfo_intercompany/README.rst
odoo/addons/product_supplierinfo_intercompany/__init__.py
odoo/addons/product_supplierinfo_intercompany/__manifest__.py
odoo/addons/product_supplierinfo_intercompany/demo/pricelist.xml
odoo/addons/product_supplierinfo_intercompany/i18n/fr.po
odoo/addons/product_supplierinfo_intercompany/i18n/it.po
odoo/addons/product_supplierinfo_intercompany/i18n/product_supplier_intercompany.pot
odoo/addons/product_supplierinfo_intercompany/i18n/product_supplierinfo_intercompany.pot
odoo/addons/product_supplierinfo_intercompany/models/__init__.py
odoo/addons/product_supplierinfo_intercompany/models/product_intercompany_supplier_mixin.py
odoo/addons/product_supplierinfo_intercompany/models/product_pricelist.py
odoo/addons/product_supplierinfo_intercompany/models/product_pricelist_item.py
odoo/addons/product_supplierinfo_intercompany/models/product_product.py
odoo/addons/product_supplierinfo_intercompany/models/product_supplierinfo.py
odoo/addons/product_supplierinfo_intercompany/models/product_template.py
odoo/addons/product_supplierinfo_intercompany/models/purchase_order.py
odoo/addons/product_supplierinfo_intercompany/readme/CONTRIBUTORS.rst
odoo/addons/product_supplierinfo_intercompany/readme/DESCRIPTION.rst
odoo/addons/product_supplierinfo_intercompany/readme/USAGE.rst
odoo/addons/product_supplierinfo_intercompany/security/supplierinfo.xml
odoo/addons/product_supplierinfo_intercompany/static/description/icon.png
odoo/addons/product_supplierinfo_intercompany/static/description/index.html
odoo/addons/product_supplierinfo_intercompany/tests/__init__.py
odoo/addons/product_supplierinfo_intercompany/tests/test_supplier_intercompany.py
odoo/addons/product_supplierinfo_intercompany/views/pricelist_views.xml
odoo14_addon_product_supplierinfo_intercompany-14.0.1.1.1.dist-info/METADATA
odoo14_addon_product_supplierinfo_intercompany-14.0.1.1.1.dist-info/WHEEL
odoo14_addon_product_supplierinfo_intercompany-14.0.1.1.1.dist-info/top_level.txt
odoo14_addon_product_supplierinfo_intercompany-14.0.1.1.1.dist-info/RECORD
