Metadata-Version: 2.1
Name: odoo14-addon-product-supplierinfo-intercompany
Version: 14.0.1.1.1
Summary: Product SupplierInfo Intercompany
Home-page: https://github.com/OCA/multi-company
Author: Odoo Community Association (OCA), Akretion
Author-email: support@odoo-community.org
License: AGPL-3
Platform: UNKNOWN
Classifier: Programming Language :: Python
Classifier: Framework :: Odoo
Classifier: Framework :: Odoo :: 14.0
Classifier: License :: OSI Approved :: GNU Affero General Public License v3
Requires-Python: >=3.6
Requires-Dist: odoo14-addon-purchase-sale-inter-company
Requires-Dist: odoo <14.1dev,>=14.0a
